streamstore/__init__.py
streamstore/_client.py
streamstore/_exceptions.py
streamstore/_mappers.py
streamstore/_retrier.py
streamstore/py.typed
streamstore/schemas.py
streamstore/utils.py
streamstore/_lib/__init__.py
streamstore/_lib/s2/__init__.py
streamstore/_lib/s2/v1alpha/s2_pb2.py
streamstore/_lib/s2/v1alpha/s2_pb2.pyi
streamstore/_lib/s2/v1alpha/s2_pb2_grpc.py
streamstore-5.0.0.dist-info/METADATA
streamstore-5.0.0.dist-info/WHEEL
streamstore-5.0.0.dist-info/licenses/LICENSE
streamstore-5.0.0.dist-info/RECORD
