Metadata-Version: 2.4
Name: streamstore
Version: 5.0.0
Summary: Python SDK for s2.dev
License-File: LICENSE
Requires-Python: >=3.11
Requires-Dist: anyio>=4.8.0
Requires-Dist: grpc-stubs>=1.53.0.5
Requires-Dist: grpcio-tools>=1.69.0
Requires-Dist: grpcio>=1.69.0
Requires-Dist: types-protobuf>=5.29.1.20241207
